AUTHORS.rst
CHANGES.rst
CONTRIBUTING.rst
LICENSE
MANIFEST.in
README.rst
setup.py
pep438/__init__.py
pep438/core.py
pep438/main.py
pep438.egg-info/PKG-INFO
pep438.egg-info/SOURCES.txt
pep438.egg-info/dependency_links.txt
pep438.egg-info/entry_points.txt
pep438.egg-info/requires.txt
pep438.egg-info/top_level.txt