Metadata-Version: 1.1
Name: pep438
Version: 0.3.0
Summary: Check your requirements for proper PEP 438 usage.
Home-page: https://github.com/treyhunner/pep438
Author: Trey Hunner
Author-email: UNKNOWN
License: The MIT License (MIT)
